partial_tables/__init__.py
partial_tables/partial_table.py
partial_tables-0.0.2.dist-info/METADATA
partial_tables-0.0.2.dist-info/WHEEL
partial_tables-0.0.2.dist-info/licenses/LICENSE
partial_tables-0.0.2.dist-info/RECORD
