Metadata-Version: 2.4
Name: partial-tables
Version: 0.0.2
Summary: Partial Table Models for SQLAlchemy and SQLModel
License-File: LICENSE
Author: Julien Kmec
Author-email: me@julien.dev
Requires-Python: >=3.11,<3.15
Classifier: Programming Language :: Python :: 3
Classifier: Programming Language :: Python :: 3.11
Classifier: Programming Language :: Python :: 3.12
Classifier: Programming Language :: Python :: 3.13
Classifier: Programming Language :: Python :: 3.14
Provides-Extra: dev
Requires-Dist: black ; extra == "dev"
Requires-Dist: isort ; extra == "dev"
Requires-Dist: psycopg2-binary (>=2.9.10)
Requires-Dist: pylint ; extra == "dev"
Requires-Dist: pytest (>=8.3.5) ; extra == "dev"
Requires-Dist: pytest-asyncio (>=0.26.0) ; extra == "dev"
Requires-Dist: pytest-cov (>=6.1.1) ; extra == "dev"
Requires-Dist: pytest-docker (>=3.2.1) ; extra == "dev"
Requires-Dist: pytest-sqlalchemy (>=0.3.0) ; extra == "dev"
Requires-Dist: sqlalchemy (>=2.0.40)
Requires-Dist: sqlalchemy-utils (>=0.41.2)
Requires-Dist: sqlmodel (>=0.0.24)
Project-URL: Repository, https://github.com/julien777z/partial-tables
